btyd/__init__.py
btyd/datasets/CDNOW_master.txt
btyd/datasets/CDNOW_sample.txt
btyd/datasets/__init__.py
btyd/datasets/cdnow_customers_summary.csv
btyd/datasets/cdnow_customers_summary_with_transactions.csv
btyd/datasets/donations.csv
btyd/datasets/example_transactions.csv
btyd/fitters/__init__.py
btyd/fitters/beta_geo_beta_binom_fitter.py
btyd/fitters/beta_geo_covar_fitter.py
btyd/fitters/beta_geo_fitter.py
btyd/fitters/gamma_gamma_fitter.py
btyd/fitters/modified_beta_geo_fitter.py
btyd/fitters/pareto_nbd_fitter.py
btyd/generate_data.py
btyd/models/__init__.py
btyd/models/beta_geo_model.py
btyd/models/gamma_gamma_model.py
btyd/models/mod_beta_geo_model.py
btyd/plotting.py
btyd/utils.py
btyd-0.1b3.dist-info/LICENSE.txt
btyd-0.1b3.dist-info/WHEEL
btyd-0.1b3.dist-info/METADATA
btyd-0.1b3.dist-info/RECORD
