Metadata-Version: 2.1
Name: btyd
Version: 0.1b3
Summary: Buy Till You Die and Customer Lifetime Value statistical models in Python.
License: Apache 2.0
Author: Colt Allen
Requires-Python: >=3.8,<3.10
Classifier: License :: Other/Proprietary License
Classifier: Programming Language :: Python :: 3
Classifier: Programming Language :: Python :: 3.8
Classifier: Programming Language :: Python :: 3.9
Requires-Dist: autograd (==1.4)
Requires-Dist: numpy (>=1.20.0,<2.0.0)
Requires-Dist: pymc (>=4.0.0,<5.0.0)
